{
    "baterka": {
        "title": "Oprava rozbitého displeja",
        "photoUrl": "/img/icons/X-12/displej.png",
        "price": 230,
        "note": "Vhodné pri rozbitom alebo poškrabanom displeji.",
        "detail_desc": [
            {
                "cat": 3,
                "src": "img/photos/IMG_3439.JPG"
            },
            {
                "cat": 1,
                "note": "Toto je podrobna poznamka 1."
            },
            {
                "cat": 1,
                "note": "Toto je podrobna poznamka 2."
            },
            {
                "cat": 2,
                "title": "Nadpis zoznamu",
                "points": [
                    "Toto je poznamka 1.",
                    "Toto je poznamka 2",
                    "Toto je nejaka dalsia poznamka."
                ]
            }
        ]
    },
    "displej": {
        "title": "Item 2",
        "photoUrl": "/img/icons/X-12/reprak.png",
        "price": 100,
        "note": "Toto je poznamka ktora sa vypise pri danom prvku, konkretne pri pokazenom reproduktore.",
        "detail_desc": "Toto je podrobny popis produktu"
    },
    "home-button": {
        "title": "Item 3",
        "photoUrl": "/img/icons/X-12/reprak.png",
        "price": 100,
        "note": "Toto je poznamka ktora sa vypise pri danom prvku, konkretne pri pokazenom reproduktore."
    },
    "reproduktor": {
        "title": "Item 3",
        "photoUrl": "/img/icons/X-12/reprak.png",
        "price": 100,
        "note": "Toto je poznamka ktora sa vypise pri danom prvku, konkretne pri pokazenom reproduktore."
    }
}